aviary/envs/notebook/__init__.py
aviary/envs/notebook/config.py
aviary/envs/notebook/env.py
aviary/envs/notebook/py.typed
aviary/envs/notebook/utils.py
aviary/envs/notebook/version.py
aviary_notebook-0.32.0.dist-info/METADATA
aviary_notebook-0.32.0.dist-info/WHEEL
aviary_notebook-0.32.0.dist-info/top_level.txt
aviary_notebook-0.32.0.dist-info/RECORD
