Metadata-Version: 2.4
Name: aviary.notebook
Version: 0.32.0
Summary: Jupyter notebook environment implemented with aviary
Author-email: FutureHouse technical staff <hello@futurehouse.org>
Classifier: Intended Audience :: Developers
Classifier: License :: OSI Approved :: Apache Software License
Classifier: Operating System :: OS Independent
Classifier: Programming Language :: Python :: 3 :: Only
Classifier: Programming Language :: Python :: 3.11
Classifier: Programming Language :: Python :: 3.12
Classifier: Programming Language :: Python :: 3.13
Classifier: Programming Language :: Python :: 3.14
Classifier: Programming Language :: Python
Classifier: Topic :: Scientific/Engineering :: Artificial Intelligence
Requires-Python: >=3.11
Requires-Dist: Pillow
Requires-Dist: aiodocker
Requires-Dist: fhaviary
Requires-Dist: ipykernel
Requires-Dist: jupyter-client
Requires-Dist: litellm
Requires-Dist: nbformat
Requires-Dist: numpy
Requires-Dist: pydantic~=2.0
Provides-Extra: dev
Requires-Dist: matplotlib; extra == "dev"
